setup.py
FbBirthday/Authentication.py
FbBirthday/Facebook_Creds.py
FbBirthday/Happy_Birthday.py
FbBirthday/Notification.py
FbBirthday/___init__.py
FbBirthday/cron_emulate.py
FbBirthday/python_cronjob_setter.py
FbBirthday/scheduler.py
FbBirthday/xpaths.py
FbBirthday.egg-info/PKG-INFO
FbBirthday.egg-info/SOURCES.txt
FbBirthday.egg-info/dependency_links.txt
FbBirthday.egg-info/entry_points.txt
FbBirthday.egg-info/requires.txt
FbBirthday.egg-info/top_level.txt
FbBirthday.egg-info/zip-safe