Metadata-Version: 1.0
Name: FbBirthday
Version: 0.1
Summary: Schedule your Birthday wishes for your facebook friends and never Miss any birthdays
Home-page: http://github.com/storborg/funniest
Author: Ankit Mishra
Author-email: ankitmishra@gmail.com
License: MIT
Platform: UNKNOWN
